travelagent1/__init__.py
travelagent1-0.0.1.dist-info/METADATA
travelagent1-0.0.1.dist-info/WHEEL
travelagent1-0.0.1.dist-info/licenses/LICENSE
travelagent1-0.0.1.dist-info/RECORD
